pypipackagestats/__init__.py
pypipackagestats/api.py
pypipackagestats/cli.py
pypipackagestats/core/__init__.py
pypipackagestats/core/cache.py
pypipackagestats/core/client.py
pypipackagestats/core/constants.py
pypipackagestats/core/exceptions.py
pypipackagestats/core/metadata.py
pypipackagestats/core/models.py
pypipackagestats/core/processing.py
pypipackagestats/output/__init__.py
pypipackagestats/output/formatters.py
pypipackagestats/output/utils.py
pypipackagestats/pyproject.toml
pypi_package_stats-1.4.0.dist-info/METADATA
pypi_package_stats-1.4.0.dist-info/WHEEL
pypi_package_stats-1.4.0.dist-info/entry_points.txt
pypi_package_stats-1.4.0.dist-info/licenses/LICENSE
pypi_package_stats-1.4.0.dist-info/RECORD
