Metadata-Version: 2.4
Name: pypi-package-stats
Version: 1.4.0
Summary: A CLI tool and Python library for PyPI package stats and download analytics, built on the official pypistats API. Fetch daily, weekly, monthly, and 180-day downloads, Python version and OS breakdowns, package metadata, with smart disk caching.
Project-URL: Homepage, https://github.com/ysskrishna/pypi-package-stats
Project-URL: Documentation, https://ysskrishna.github.io/pypi-package-stats/
Project-URL: Repository, https://github.com/ysskrishna/pypi-package-stats.git
Project-URL: Issues, https://github.com/ysskrishna/pypi-package-stats/issues
Author-email: ysskrishna <sivasaikrishnassk@gmail.com>
License: MIT
License-File: LICENSE
Keywords: caching,cli,download-stats,json,package-analytics,package-downloads,package-info,package-metadata,package-metrics,package-stats,pypi,pypi-api,pypi-downloads,pypi-package-info,pypi-stats,pypistats
Classifier: Development Status :: 5 - Production/Stable
Classifier: Intended Audience :: Developers
Classifier: Intended Audience :: System Administrators
Classifier: License :: OSI Approved :: MIT License
Classifier: Operating System :: OS Independent
Classifier: Programming Language :: Python :: 3
Classifier: Programming Language :: Python :: 3.8
Classifier: Programming Language :: Python :: 3.9
Classifier: Programming Language :: Python :: 3.10
Classifier: Programming Language :: Python :: 3.11
Classifier: Programming Language :: Python :: 3.12
Classifier: Topic :: Software Development :: Libraries :: Python Modules
Classifier: Topic :: Utilities
Requires-Python: >=3.8
Requires-Dist: diskcache>=5.6.0
Requires-Dist: nestedutils==1.1.2
Requires-Dist: platformdirs>=3.0.0
Requires-Dist: requests>=2.31.0
Requires-Dist: rich>=13.0.0
Requires-Dist: tomli>=2.1.0; python_version < '3.11'
Requires-Dist: typer>=0.9.0
